deczoo/__init__.py
deczoo/_base_notifier.py
deczoo/_utils.py
deczoo/decorators.py
deczoo/py.typed
deczoo-0.6.0.dist-info/METADATA
deczoo-0.6.0.dist-info/WHEEL
deczoo-0.6.0.dist-info/licenses/LICENSE
deczoo-0.6.0.dist-info/RECORD
