Metadata-Version: 2.1
Name: deczoo
Version: 0.6.0
Summary: Zoo for Python decorators
Project-URL: documentation, https://fbruzzesi.github.io/deczoo/
Project-URL: repository, https://github.com/fbruzzesi/deczoo
Project-URL: issue-tracker, https://github.com/fbruzzesi/deczoo/issues
Author: Francesco Bruzzesi
License: MIT License
License-File: LICENSE
Classifier: License :: OSI Approved :: MIT License
Classifier: Programming Language :: Python :: 3
Classifier: Programming Language :: Python :: 3.8
Classifier: Programming Language :: Python :: 3.9
Classifier: Programming Language :: Python :: 3.10
Classifier: Programming Language :: Python :: 3.11
Classifier: Programming Language :: Python :: 3.12
Requires-Python: >=3.8
Requires-Dist: typing-extensions>=4.4.0; python_version < '3.12'
Provides-Extra: all
Requires-Dist: deczoo[chime,rich]; extra == 'all'
Provides-Extra: all-dev
Requires-Dist: deczoo[chime,dev,docs,lint,rich,test]; extra == 'all-dev'
Provides-Extra: chime
Requires-Dist: chime; extra == 'chime'
Provides-Extra: dev
Requires-Dist: hatch; extra == 'dev'
Requires-Dist: pre-commit>=2.21.0; extra == 'dev'
Provides-Extra: docs
Requires-Dist: mkdocs-material>=9.1.2; extra == 'docs'
Requires-Dist: mkdocs>=1.4.2; extra == 'docs'
Requires-Dist: mkdocstrings[python]>=0.20.0; extra == 'docs'
Provides-Extra: lint
Requires-Dist: ruff>=0.1.6; extra == 'lint'
Provides-Extra: rich
Requires-Dist: rich>=12.0.0; extra == 'rich'
Provides-Extra: test
Requires-Dist: coverage-badge>=1.1.0; extra == 'test'
Requires-Dist: coverage>=7.2.1; extra == 'test'
Requires-Dist: interrogate>=1.5.0; extra == 'test'
Requires-Dist: numpy; extra == 'test'
Requires-Dist: pytest-xdist>=3.2.1; extra == 'test'
Requires-Dist: pytest>=7.2.0; extra == 'test'
